packtype/__init__.py
packtype/__main__.py
packtype/alias.py
packtype/array.py
packtype/assembly.py
packtype/base.py
packtype/bitvector.py
packtype/common/pt_axi4lite_bridge.sv
packtype/common/pt_fifo.sv
packtype/constant.py
packtype/enum.py
packtype/mkdocs/__init__.py
packtype/mkdocs/plugin.py
packtype/numeric.py
packtype/package.py
packtype/packing.py
packtype/primitive.py
packtype/registers.py
packtype/scalar.py
packtype/struct.py
packtype/svg/__init__.py
packtype/svg/render.py
packtype/templates/blocks.mako
packtype/templates/common.py
packtype/templates/header.mako
packtype/templates/package.sv.mako
packtype/templates/register_access.hpp.mako
packtype/templates/register_access.py.mako
packtype/templates/register_file.sv.mako
packtype/templates/register_pkg.sv.mako
packtype/union.py
packtype/utils.py
packtype/wrap.py
packtype-2.1.0.dist-info/LICENSE
packtype-2.1.0.dist-info/METADATA
packtype-2.1.0.dist-info/WHEEL
packtype-2.1.0.dist-info/RECORD
