Metadata-Version: 2.3
Name: packtype
Version: 2.1.0
Summary: Packed data structure specifications for multi-language hardware projects
License: Apache-2.0
Author: Peter Birch
Author-email: peter@intuity.io
Requires-Python: >=3.11,<4.0
Classifier: License :: OSI Approved :: Apache Software License
Classifier: Programming Language :: Python :: 3
Classifier: Programming Language :: Python :: 3.11
Classifier: Programming Language :: Python :: 3.12
Classifier: Programming Language :: Python :: 3.13
Requires-Dist: Mako (>=1.3.0,<2.0.0)
Requires-Dist: click (>=8.1.7,<9.0.0)
Requires-Dist: ordered-set (>=4.1.0,<5.0.0)
Requires-Dist: rich (>=13.7.0,<14.0.0)
Requires-Dist: svg-py (>=1.4.3,<2.0.0)
Requires-Dist: typing-extensions (>=4.8.0,<5.0.0)
